prismacloud/__init__.py
prismacloud/cli/__init__.py
prismacloud/cli/api.py
prismacloud/cli/version.py
prismacloud/cli/cspm/__init__.py
prismacloud/cli/cspm/cmd_alert.py
prismacloud/cli/cspm/cmd_check.py
prismacloud/cli/cspm/cmd_cloud.py
prismacloud/cli/cspm/cmd_compliance.py
prismacloud/cli/cspm/cmd_current.py
prismacloud/cli/cspm/cmd_iam.py
prismacloud/cli/cspm/cmd_inventory.py
prismacloud/cli/cspm/cmd_licenses.py
prismacloud/cli/cspm/cmd_policy.py
prismacloud/cli/cspm/cmd_pov.py
prismacloud/cli/cspm/cmd_resource.py
prismacloud/cli/cspm/cmd_rql.py
prismacloud/cli/cspm/cmd_saas_version.py
prismacloud/cli/cspm/cmd_usage.py
prismacloud/cli/cwpp/__init__.py
prismacloud/cli/cwpp/cmd_audits.py
prismacloud/cli/cwpp/cmd_containers.py
prismacloud/cli/cwpp/cmd_credentials.py
prismacloud/cli/cwpp/cmd_defenders.py
prismacloud/cli/cwpp/cmd_discovery.py
prismacloud/cli/cwpp/cmd_host_auto_deploy.py
prismacloud/cli/cwpp/cmd_hosts.py
prismacloud/cli/cwpp/cmd_images.py
prismacloud/cli/cwpp/cmd_incidents.py
prismacloud/cli/cwpp/cmd_intelligence.py
prismacloud/cli/cwpp/cmd_license.py
prismacloud/cli/cwpp/cmd_logs.py
prismacloud/cli/cwpp/cmd_monitor.py
prismacloud/cli/cwpp/cmd_policies.py
prismacloud/cli/cwpp/cmd_registry.py
prismacloud/cli/cwpp/cmd_scans.py
prismacloud/cli/cwpp/cmd_serverless_auto_deploy.py
prismacloud/cli/cwpp/cmd_settings.py
prismacloud/cli/cwpp/cmd_stats.py
prismacloud/cli/cwpp/cmd_tags.py
prismacloud/cli/cwpp/cmd_users.py
prismacloud/cli/cwpp/cmd_version.py
prismacloud/cli/pccs/__init__.py
prismacloud/cli/pccs/cmd_repositories.py
prismacloud/cli/pccs/cmd_reviews.py
prismacloud/cli/pccs/cmd_suppressions.py
tests/test_cli.py
prismacloud_cli-0.8.11.dist-info/LICENSE
prismacloud_cli-0.8.11.dist-info/METADATA
prismacloud_cli-0.8.11.dist-info/WHEEL
prismacloud_cli-0.8.11.dist-info/entry_points.txt
prismacloud_cli-0.8.11.dist-info/top_level.txt
prismacloud_cli-0.8.11.dist-info/RECORD
