Metadata-Version: 2.1
Name: prismacloud-cli
Version: 0.8.11
Summary: Prisma Cloud CLI
Home-page: https://github.com/PaloAltoNetworks/prismacloud-cli
Author: Steven de Boer, Simon Melotte, Tom Kishel
Author-email: stdeboer@paloaltonetworks.com, smelotte@paloaltonetworks.com, tkishel@paloaltonetworks.com
License: BSD
Keywords: prisma cloud cli
Classifier: Development Status :: 3 - Alpha
Classifier: Intended Audience :: Developers
Classifier: Intended Audience :: System Administrators
Classifier: License :: OSI Approved :: MIT License
Classifier: Programming Language :: Python
Classifier: Topic :: Utilities
Requires-Python: >=3.7
License-File: LICENSE
Requires-Dist: api-client
Requires-Dist: click
Requires-Dist: click-completion
Requires-Dist: click-help-colors
Requires-Dist: coloredlogs
Requires-Dist: jsondiff
Requires-Dist: pandas
Requires-Dist: requests
Requires-Dist: tabulate
Requires-Dist: colorama
Requires-Dist: update-checker
Requires-Dist: pydantic-settings
Requires-Dist: pydantic
Requires-Dist: datetime
Requires-Dist: pyyaml
Requires-Dist: prismacloud-api ==5.2.24
Requires-Dist: pytest
Requires-Dist: pytest-benchmark
